LICENSE
README.md
setup.cfg
setup.py
dendro_text/Blocks.txt
dendro_text/VERSION
dendro_text/__init__.py
dendro_text/commands.py
dendro_text/dld.py
dendro_text/main.py
dendro_text/print_tree.py
dendro_text/ts.py
dendro_text.egg-info/PKG-INFO
dendro_text.egg-info/SOURCES.txt
dendro_text.egg-info/dependency_links.txt
dendro_text.egg-info/entry_points.txt
dendro_text.egg-info/requires.txt
dendro_text.egg-info/top_level.txt
tests/__init__.py
tests/test_dld.py
tests/test_merge_identical_docs.py
tests/test_preprocessing.py
tests/test_print_diff.py
tests/test_print_tree.py
tests/test_text_split.py