Metadata-Version: 2.1
Name: dendro-text
Version: 1.5.3
Summary: Draw dendrogram of similarity between text files
Home-page: https://github.com/tos-kamiya/dendro_text
Author: Toshihiro Kamiya
Author-email: kamiya@mbj.nifty.com
License: BSD 2-Clause License
Classifier: Programming Language :: Python :: 3.8
Classifier: Programming Language :: Python :: 3.9
Classifier: Programming Language :: Python :: 3.10
Classifier: License :: OSI Approved :: BSD License
Classifier: Operating System :: MacOS :: MacOS X
Classifier: Operating System :: POSIX :: Linux
Classifier: Operating System :: Microsoft :: Windows
Requires-Python: >=3.8
Provides-Extra: docopt-ng
Provides-Extra: docopt
License-File: LICENSE
